danbooru_tag_graph/__init__.py
danbooru_tag_graph/danbooru_tag_graph.py
danbooru_tag_graph-0.2.2.dist-info/licenses/LICENSE
danbooru_tag_graph-0.2.2.dist-info/METADATA
danbooru_tag_graph-0.2.2.dist-info/WHEEL
danbooru_tag_graph-0.2.2.dist-info/top_level.txt
danbooru_tag_graph-0.2.2.dist-info/RECORD
