Metadata-Version: 2.4
Name: danbooru-tag-graph
Version: 0.2.2
Summary: Represent Danbooru folksonomy as a directed graph
Author-email: Allen Day <allenday@users.github.com>
Maintainer-email: Allen Day <allenday@users.github.com>
License: MIT
Project-URL: Homepage, https://github.com/allenday/danbooru-tag-graph
Project-URL: Documentation, https://github.com/allenday/danbooru-tag-graph#readme
Project-URL: Repository, https://github.com/allenday/danbooru-tag-graph.git
Project-URL: Bug Tracker, https://github.com/allenday/danbooru-tag-graph/issues
Project-URL: Changelog, https://github.com/allenday/danbooru-tag-graph/releases
Keywords: danbooru,tags,image,tagging,api,booru
Classifier: Development Status :: 3 - Alpha
Classifier: Intended Audience :: Developers
Classifier: Operating System :: OS Independent
Classifier: Programming Language :: Python :: 3
Classifier: Programming Language :: Python :: 3.6
Classifier: Programming Language :: Python :: 3.7
Classifier: Programming Language :: Python :: 3.8
Classifier: Programming Language :: Python :: 3.9
Classifier: Programming Language :: Python :: 3.10
Classifier: Programming Language :: Python :: 3.11
Classifier: Programming Language :: Python :: 3.12
Classifier: Topic :: Internet :: WWW/HTTP :: Dynamic Content
Classifier: Topic :: Software Development :: Libraries :: Python Modules
Classifier: Topic :: Multimedia :: Graphics
Requires-Python: >=3.6
License-File: LICENSE
Requires-Dist: networkx>=2.5
Provides-Extra: dev
Requires-Dist: pytest>=6.0; extra == "dev"
Requires-Dist: pytest-cov>=2.10.0; extra == "dev"
Requires-Dist: black>=21.0.0; extra == "dev"
Requires-Dist: flake8>=3.8.0; extra == "dev"
Requires-Dist: mypy>=0.800; extra == "dev"
Requires-Dist: build>=0.7.0; extra == "dev"
Requires-Dist: twine>=3.0.0; extra == "dev"
Provides-Extra: test
Requires-Dist: pytest>=6.0; extra == "test"
Requires-Dist: pytest-cov>=2.10.0; extra == "test"
Dynamic: license-file
